xsh/__init__.py
xsh/host.py
xsh/key.py
xsh/main.py
xsh-0.1.4.dist-info/LICENSE.txt
xsh-0.1.4.dist-info/METADATA
xsh-0.1.4.dist-info/WHEEL
xsh-0.1.4.dist-info/entry_points.txt
xsh-0.1.4.dist-info/top_level.txt
xsh-0.1.4.dist-info/RECORD
