Metadata-Version: 2.1
Name: xsh
Version: 0.1.4
Summary: ssh config manager
Author-email: Zilong ZHOU <zzl0712@outlook.com>
Maintainer-email: Zilong ZHOU <zzl0712@outlook.com>
License: Copyright (c) 2016 The Python Packaging Authority (PyPA)
Keywords: cl,ssh
Classifier: Development Status :: 3 - Alpha
Classifier: Intended Audience :: Developers
Classifier: Topic :: Software Development :: Build Tools
Classifier: License :: OSI Approved :: MIT License
Classifier: Programming Language :: Python :: 3
Classifier: Programming Language :: Python :: 3.7
Classifier: Programming Language :: Python :: 3.8
Classifier: Programming Language :: Python :: 3.9
Classifier: Programming Language :: Python :: 3.10
Classifier: Programming Language :: Python :: 3.11
Classifier: Programming Language :: Python :: 3 :: Only
Requires-Python: >=3.7
License-File: LICENSE.txt
Requires-Dist: argparse
Provides-Extra: dev
Requires-Dist: check-manifest ; extra == 'dev'
Provides-Extra: test
Requires-Dist: coverage ; extra == 'test'
